mailkit/__init__.py
mailkit/version.json
mailkit/bin/__init__.py
mailkit/bin/_config.py
mailkit/bin/_send.py
mailkit/bin/main.py
mailkit/config/__init__.py
mailkit/core/__init__.py
mailkit/core/message.py
mailkit/core/smtp.py
mailkit/core/smtp/__init__.py
mailkit/core/smtp/config.py
mailkit/core/smtp/mail.py
mailkit/core/smtp/message.py
mailkit/core/smtp/sendemail.py
mailkit/error/__init__.py
mailkit-1.0.2.dist-info/METADATA
mailkit-1.0.2.dist-info/WHEEL
mailkit-1.0.2.dist-info/entry_points.txt
mailkit-1.0.2.dist-info/top_level.txt
mailkit-1.0.2.dist-info/RECORD
