Metadata-Version: 2.1
Name: mailkit
Version: 1.0.2
Summary: A user-friendly Python email toolkit
Home-page: https://github.com/suqingdong/mailkit
Author: suqingdong
Author-email: suqingdong1114@gmail.com
License: MIT License
Project-URL: Documentation, https://mailkit.readthedocs.io
Project-URL: Tracker, https://github.com/suqingdong/mailkit/issues
Platform: UNKNOWN
Classifier: Development Status :: 5 - Production/Stable
Classifier: Operating System :: OS Independent
Classifier: Intended Audience :: Developers
Classifier: License :: OSI Approved :: MIT License
Classifier: Programming Language :: Python
Classifier: Programming Language :: Python :: 3 :: Only
Classifier: Programming Language :: Python :: 3.9
Classifier: Programming Language :: Python :: 3.10
Classifier: Programming Language :: Python :: 3.11
Classifier: Topic :: Software Development :: Libraries
Requires-Python: >=3.9
Requires-Dist: click (>=8.1.3)
Requires-Dist: pydantic-settings (>=2.0.3)
